amberNPS/__init__.py
amberNPS/api.py
amberNPS/models/label_encoder.pkl
amberNPS/models/multitask_regressor.pkl
amberNPS/models/random_forest_model.pkl
amberNPS/models/scaler.pkl
ambernps-0.1.6.dist-info/licenses/LICENSE
ambernps-0.1.6.dist-info/METADATA
ambernps-0.1.6.dist-info/WHEEL
ambernps-0.1.6.dist-info/top_level.txt
ambernps-0.1.6.dist-info/RECORD
