Metadata-Version: 2.4
Name: amberNPS
Version: 0.1.6
Summary: A python api to make lethal blood concentrations using amberNPS
Home-page: https://github.com/dpasin/amberNPS-api
Author: Daniel Pasin
Author-email: daniel.pasin@hyperiondata.org
License: MIT
Keywords: amberNPS,chemistry,toxicology
Classifier: Development Status :: 4 - Beta
Classifier: Intended Audience :: Science/Research
Classifier: Topic :: Scientific/Engineering :: Chemistry
Classifier: Topic :: Scientific/Engineering :: Medical Science Apps.
Classifier: Programming Language :: Python
License-File: LICENSE
Requires-Dist: numpy
Requires-Dist: pandas
Requires-Dist: rdkit
Requires-Dist: mordredcommunity
Requires-Dist: scikit-learn==1.6.1
Dynamic: author
Dynamic: author-email
Dynamic: classifier
Dynamic: description
Dynamic: description-content-type
Dynamic: home-page
Dynamic: keywords
Dynamic: license
Dynamic: license-file
Dynamic: requires-dist
Dynamic: summary
